pyshtools/_SHTOOLS.cpython-311-x86_64-linux-gnu.so
pyshtools/__init__.py
pyshtools/backends/__init__.py
pyshtools/backends/backends.py
pyshtools/backends/ducc0_wrapper.py
pyshtools/backends/shtools.py
pyshtools/constants/Callisto.py
pyshtools/constants/Ceres.py
pyshtools/constants/Charon.py
pyshtools/constants/Earth.py
pyshtools/constants/Enceladus.py
pyshtools/constants/Eros.py
pyshtools/constants/Europa.py
pyshtools/constants/Ganymede.py
pyshtools/constants/Io.py
pyshtools/constants/Jupiter.py
pyshtools/constants/Mars.py
pyshtools/constants/Mercury.py
pyshtools/constants/Moon.py
pyshtools/constants/Neptune.py
pyshtools/constants/Pluto.py
pyshtools/constants/Psyche.py
pyshtools/constants/Saturn.py
pyshtools/constants/Sun.py
pyshtools/constants/Titan.py
pyshtools/constants/Uranus.py
pyshtools/constants/Venus.py
pyshtools/constants/Vesta.py
pyshtools/constants/__init__.py
pyshtools/datasets/Callisto.py
pyshtools/datasets/Ceres.py
pyshtools/datasets/Enceladus.py
pyshtools/datasets/Eros.py
pyshtools/datasets/Europa.py
pyshtools/datasets/Ganymede.py
pyshtools/datasets/Io.py
pyshtools/datasets/Jupiter.py
pyshtools/datasets/Mercury.py
pyshtools/datasets/Neptune.py
pyshtools/datasets/Psyche.py
pyshtools/datasets/Saturn.py
pyshtools/datasets/Titan.py
pyshtools/datasets/Uranus.py
pyshtools/datasets/Vesta.py
pyshtools/datasets/__init__.py
pyshtools/datasets/Earth/__init__.py
pyshtools/datasets/Earth/Earth2012/__init__.py
pyshtools/datasets/Earth/Earth2014/__init__.py
pyshtools/datasets/Mars/__init__.py
pyshtools/datasets/Mars/historical/__init__.py
pyshtools/datasets/Mars/historical/gravity.py
pyshtools/datasets/Mars/historical/magnetic.py
pyshtools/datasets/Mars/historical/shape.py
pyshtools/datasets/Moon/__init__.py
pyshtools/datasets/Moon/historical/__init__.py
pyshtools/datasets/Moon/historical/gravity.py
pyshtools/datasets/Moon/historical/shape.py
pyshtools/datasets/Venus/__init__.py
pyshtools_glibc_compat-4.13.1.dist-info/METADATA
pyshtools_glibc_compat-4.13.1.dist-info/WHEEL
pyshtools_glibc_compat-4.13.1.dist-info/RECORD
